{"author": "django", "code": "from django.conf.urls import url\n\nfrom . import views\n\nurlpatterns = [\n    url(r'^innocent/$', views.innocent),\n    url(r'^suspicious/$', views.suspicious),\n    url(r'^suspicious_spec/$', views.suspicious_spec),\n]\n", "comments": "", "content": "from django.conf.urls import url\n\nfrom . import views\n\nurlpatterns = [\n    url(r'^innocent/$', views.innocent),\n    url(r'^suspicious/$', views.suspicious),\n    url(r'^suspicious_spec/$', views.suspicious_spec),\n]\n", "description": "The Web framework for perfectionists with deadlines.", "file_name": "urls.py", "id": "004576c9099ab163de6f7862e35742c3", "language": "Python", "project_name": "django", "quality": "", "save_path": "/home/ubuntu/test_files/clean/python/django-django/django-django-274e3e2/tests/logging_tests/urls.py", "save_time": "", "source": "", "update_at": "2018-03-18T13:39:10Z", "url": "https://github.com/django/django", "wiki": false}