{"author": "django", "code": "\n\n", "comments": "  this module exist  otherwise pre post migrate sent    migrate signals application  ", "content": "# This module has to exist, otherwise pre/post_migrate aren't sent for the\n# migrate_signals application.\n", "description": "The Web framework for perfectionists with deadlines.", "file_name": "models.py", "id": "29c8da943ea8b6fb2e18b90b0d22c0f7", "language": "Python", "project_name": "django", "quality": "", "save_path": "/home/ubuntu/test_files/clean/network_test/django-django/django-django-acfc650/tests/migrate_signals/models.py", "save_time": "", "source": "", "update_at": "2018-03-14T02:00:36Z", "url": "https://github.com/django/django", "wiki": false}