{"author": "XX-net", "code": "__all__ = [\"local\", \"start\"]", "comments": "", "content": "__all__ = [\"local\", \"start\"]", "description": "a web proxy tool", "file_name": "__init__.py", "id": "4488acaadacfaf714cb9e670acbe8e54", "language": "Python", "project_name": "XX-Net", "quality": "", "save_path": "/home/ubuntu/test_files/clean/python/XX-net-XX-Net/XX-net-XX-Net-673a005/code/default/gae_proxy/__init__.py", "save_time": "", "source": "", "update_at": "2018-03-18T14:08:03Z", "url": "https://github.com/XX-net/XX-Net", "wiki": true}