{"author": "odoo", "code": "# -*- coding: utf-8 -*-\n\n\nfrom odoo import api, SUPERUSER_ID\n\n\ndef _set_accounts(cr, registry):\n    \n    env = api.Environment(cr, SUPERUSER_ID, {})\n    names = [str(x) for x in range(1,1410)]\n    data = env['ir.model.data'].search([('model', '=', 'hr.salary.rule'), ('module', '=', 'l10n_be_hr_payroll'), ('name', 'in', names)])\n    account = env['account.account'].search([('code', 'like', '4530%')], limit=1)\n    if account and data:\n        rule_ids = [x['res_id'] for x in data.read(['res_id'])]\n        env['hr.salary.rule'].browse(rule_ids).write({'account_debit': account.id})\n", "comments": "      coding  utf 8        part odoo  see license file full copyright licensing details    write default debit account salary rule xml id like  l10n hr payroll 1   l10n hr payroll 1409  ", "content": "# -*- coding: utf-8 -*-\n# Part of Odoo. See LICENSE file for full copyright and licensing details.\n\nfrom odoo import api, SUPERUSER_ID\n\n\ndef _set_accounts(cr, registry):\n    #write the default debit account on salary rule having xml_id like 'l10n_be_hr_payroll.1' up to 'l10n_be_hr_payroll.1409'\n    env = api.Environment(cr, SUPERUSER_ID, {})\n    names = [str(x) for x in range(1,1410)]\n    data = env['ir.model.data'].search([('model', '=', 'hr.salary.rule'), ('module', '=', 'l10n_be_hr_payroll'), ('name', 'in', names)])\n    account = env['account.account'].search([('code', 'like', '4530%')], limit=1)\n    if account and data:\n        rule_ids = [x['res_id'] for x in data.read(['res_id'])]\n        env['hr.salary.rule'].browse(rule_ids).write({'account_debit': account.id})\n", "description": "Odoo. Open Source Apps To Grow Your Business.", "file_name": "__init__.py", "id": "4f59bc10462cc1090c18165c098a143b", "language": "Python", "project_name": "odoo", "quality": "", "save_path": "/home/ubuntu/test_files/clean/python/odoo-odoo/odoo-odoo-b25250f/addons/l10n_be_hr_payroll_account/__init__.py", "save_time": "", "source": "", "update_at": "2018-03-18T08:30:22Z", "url": "https://github.com/odoo/odoo", "wiki": true}