{"author": "odoo", "code": "# -*- coding: utf-8 -*-\n\n{\n    'name': 'Mailing List Archive',\n    'category': 'Website',\n    'description': ,\n    'depends': ['website_mail'],\n    'data': [\n        'data/mail_template_data.xml',\n        'views/website_mail_channel_templates.xml',\n        'views/snippets.xml',\n    ],\n}\n", "comments": "    odoo mail group   mailing list archives                                                                coding  utf 8        part odoo  see license file full copyright licensing details  ", "content": "# -*- coding: utf-8 -*-\n# Part of Odoo. See LICENSE file for full copyright and licensing details.\n{\n    'name': 'Mailing List Archive',\n    'category': 'Website',\n    'description': \"\"\"\nOdoo Mail Group : Mailing List Archives\n==========================================\n\n        \"\"\",\n    'depends': ['website_mail'],\n    'data': [\n        'data/mail_template_data.xml',\n        'views/website_mail_channel_templates.xml',\n        'views/snippets.xml',\n    ],\n}\n", "description": "Odoo. Open Source Apps To Grow Your Business.", "file_name": "__manifest__.py", "id": "6508754d482cce452580facb6afe66d4", "language": "Python", "project_name": "odoo", "quality": "", "save_path": "/home/ubuntu/test_files/clean/python/odoo-odoo/odoo-odoo-b25250f/addons/website_mail_channel/__manifest__.py", "save_time": "", "source": "", "update_at": "2018-03-18T08:30:22Z", "url": "https://github.com/odoo/odoo", "wiki": true}