{"author": "newsapps", "code": "\n\ntry:\n    from setuptools import setup\nexcept ImportError:\n    from distutils.core import setup\n\nwith open('requirements.txt') as f:\n    required_packages = f.readlines()\n\nsetup(name='beeswithmachineguns',\n      version='0.1.4',\n      description='A utility for arming (creating) many bees (micro EC2 instances) to attack (load test) targets (web applications).',\n      author='Christopher Groskopf',\n      author_email='cgroskopf@tribune.com',\n      url='http://github.com/newsapps/beeswithmachineguns',\n      license='MIT',\n      packages=['beeswithmachineguns'],\n      scripts=['bees'],\n      install_requires=required_packages,\n      classifiers=[\n          'Development Status :: 4 - Beta',\n          'Environment :: Console',\n          'Intended Audience :: Developers',\n          'License :: OSI Approved :: MIT License',\n          'Natural Language :: English',\n          'Operating System :: OS Independent',\n          'Programming Language :: Python',\n          'Topic :: Software Development :: Testing :: Traffic Generation',\n          'Topic :: Utilities',\n          ],\n     )\n", "comments": "   usr bin env python ", "content": "#!/usr/bin/env python\n\ntry:\n    from setuptools import setup\nexcept ImportError:\n    from distutils.core import setup\n\nwith open('requirements.txt') as f:\n    required_packages = f.readlines()\n\nsetup(name='beeswithmachineguns',\n      version='0.1.4',\n      description='A utility for arming (creating) many bees (micro EC2 instances) to attack (load test) targets (web applications).',\n      author='Christopher Groskopf',\n      author_email='cgroskopf@tribune.com',\n      url='http://github.com/newsapps/beeswithmachineguns',\n      license='MIT',\n      packages=['beeswithmachineguns'],\n      scripts=['bees'],\n      install_requires=required_packages,\n      classifiers=[\n          'Development Status :: 4 - Beta',\n          'Environment :: Console',\n          'Intended Audience :: Developers',\n          'License :: OSI Approved :: MIT License',\n          'Natural Language :: English',\n          'Operating System :: OS Independent',\n          'Programming Language :: Python',\n          'Topic :: Software Development :: Testing :: Traffic Generation',\n          'Topic :: Utilities',\n          ],\n     )\n", "description": "A utility for arming (creating) many bees (micro EC2 instances) to attack (load test) targets (web applications).", "file_name": "setup.py", "id": "8702190e06670118235c463a36f96631", "language": "Python", "project_name": "beeswithmachineguns", "quality": "", "save_path": "/home/ubuntu/test_files/clean/python/newsapps-beeswithmachineguns/newsapps-beeswithmachineguns-4b8783d/setup.py", "save_time": "", "source": "", "update_at": "2018-03-18T02:27:44Z", "url": "https://github.com/newsapps/beeswithmachineguns", "wiki": false}