{"author": "keon", "code": "\ndef reverse_vowel(s):\n    vowels = \"AEIOUaeiou\"\n    i, j = 0, len(s)-1\n    s = list(s)\n    while i < j:\n        while i < j and s[i] not in vowels:\n            i += 1\n        while i < j and s[j] not in vowels:\n            j -= 1\n        s[i], s[j] = s[j], s[i]\n        i, j = i + 1, j - 1\n    return \"\".join(s)\n\ntest = \"hello\"\nprint(test)\nprint(reverse_vowel(test))\n", "comments": "", "content": "\ndef reverse_vowel(s):\n    vowels = \"AEIOUaeiou\"\n    i, j = 0, len(s)-1\n    s = list(s)\n    while i < j:\n        while i < j and s[i] not in vowels:\n            i += 1\n        while i < j and s[j] not in vowels:\n            j -= 1\n        s[i], s[j] = s[j], s[i]\n        i, j = i + 1, j - 1\n    return \"\".join(s)\n\ntest = \"hello\"\nprint(test)\nprint(reverse_vowel(test))\n", "description": "Minimal examples of data structures and algorithms in Python", "file_name": "reverse_vowel.py", "id": "91912e98d0eb66fbeb3f25fabb5925f8", "language": "Python", "project_name": "algorithms", "quality": "", "save_path": "/home/ubuntu/test_files/clean/python/keon-algorithms/keon-algorithms-ea43887/strings/reverse_vowel.py", "save_time": "", "source": "", "update_at": "2018-03-18T13:53:29Z", "url": "https://github.com/keon/algorithms", "wiki": true}