{"author": "odoo", "code": "# -*- coding: utf-8 -*-\n\n\n# Copyright (C) 2016 Onestein (<http://www.onestein.eu>).\n\n{\n    'name': 'Netherlands - Accounting',\n    'version': '3.0',\n    'category': 'Localization',\n    'author': 'Onestein',\n    'website': 'http://www.onestein.eu',\n    'depends': [\n        'account',\n        'base_iban',\n        'base_vat',\n        'base_address_extended',\n    ],\n    'data': [\n        'data/account_account_tag.xml',\n        'data/account_chart_template.xml',\n        'data/account.account.template.xml',\n        'data/account_data.xml',\n        'data/account_tax_template.xml',\n        'data/account_fiscal_position_template.xml',\n        'data/account_fiscal_position_tax_template.xml',\n        'data/account_fiscal_position_account_template.xml',\n        'data/account_chart_template.yml',\n        'data/menuitem.xml',\n    ],\n    'demo': [],\n    'auto_install': False,\n    'installable': True,\n}\n", "comments": "      coding  utf 8        part odoo  see license file full copyright licensing details     copyright (c) 2016 onestein ( http   www onestein eu )  ", "content": "# -*- coding: utf-8 -*-\n# Part of Odoo. See LICENSE file for full copyright and licensing details.\n\n# Copyright (C) 2016 Onestein (<http://www.onestein.eu>).\n\n{\n    'name': 'Netherlands - Accounting',\n    'version': '3.0',\n    'category': 'Localization',\n    'author': 'Onestein',\n    'website': 'http://www.onestein.eu',\n    'depends': [\n        'account',\n        'base_iban',\n        'base_vat',\n        'base_address_extended',\n    ],\n    'data': [\n        'data/account_account_tag.xml',\n        'data/account_chart_template.xml',\n        'data/account.account.template.xml',\n        'data/account_data.xml',\n        'data/account_tax_template.xml',\n        'data/account_fiscal_position_template.xml',\n        'data/account_fiscal_position_tax_template.xml',\n        'data/account_fiscal_position_account_template.xml',\n        'data/account_chart_template.yml',\n        'data/menuitem.xml',\n    ],\n    'demo': [],\n    'auto_install': False,\n    'installable': True,\n}\n", "description": "Odoo. Open Source Apps To Grow Your Business.", "file_name": "__manifest__.py", "id": "923f510d96587e2de461387d444df70f", "language": "Python", "project_name": "odoo", "quality": "", "save_path": "/home/ubuntu/test_files/clean/python/odoo-odoo/odoo-odoo-b25250f/addons/l10n_nl/__manifest__.py", "save_time": "", "source": "", "update_at": "2018-03-18T08:30:22Z", "url": "https://github.com/odoo/odoo", "wiki": true}