{"author": "ansible", "code": "\n# -*- coding: utf-8 -*-\n\n# GNU General Public License v3.0+ (see COPYING or https://www.gnu.org/licenses/gpl-3.0.txt)\n\nfrom __future__ import absolute_import, division, print_function\n__metaclass__ = type\n\nANSIBLE_METADATA = {'metadata_version': '1.1',\n                    'status': ['preview'],\n                    'supported_by': 'community'}\n\nDOCUMENTATION = r'''\n---\nmodule: aci_tenant_span_src_group\nshort_description: Manage SPAN source groups (span:SrcGrp)\ndescription:\n- Manage SPAN source groups on Cisco ACI fabrics.\nnotes:\n- The C(tenant) used must exist before using this module in your playbook.\n  The M(aci_tenant) module can be used for this.\n- More information about the internal APIC class B(span:SrcGrp) from\n  L(the APIC Management Information Model reference,https://developer.cisco.com/docs/apic-mim-ref/).\nauthor:\n- Jacob McGill (@jmcgill298)\nversion_added: '2.4'\noptions:\n  admin_state:\n    description:\n    - Enable or disable the span sources.\n    choices: [ enabled, disabled ]\n    default: enabled\n  description:\n    description:\n    - The description for Span source group.\n    aliases: [ descr ]\n  dst_group:\n    description:\n    - The Span destination group to associate with the source group.\n  src_group:\n    description:\n    - The name of the Span source group.\n    aliases: [ name ]\n  state:\n    description:\n    - Use C(present) or C(absent) for adding or removing.\n    - Use C(query) for listing an object or multiple objects.\n    choices: [ absent, present, query ]\n    default: present\n  tenant:\n    description:\n    - The name of the Tenant.\n    aliases: [ tenant_name ]\nextends_documentation_fragment: aci\n'''\n\nEXAMPLES = r'''\n- aci_tenant_span_src_group:\n    host: apic\n    username: admin\n    password: SomeSecretPassword\n    tenant: production\n    src_group: \"{{ src_group }}\"\n    dst_group: \"{{ dst_group }}\"\n    admin_state: \"{{ admin_state }}\"\n    description: \"{{ description }}\"\n'''\n\nRETURN = r'''\ncurrent:\n  description: The existing configuration from the APIC after the module has finished\n  returned: success\n  type: list\n  sample:\n    [\n        {\n            \"fvTenant\": {\n                \"attributes\": {\n                    \"descr\": \"Production environment\",\n                    \"dn\": \"uni/tn-production\",\n                    \"name\": \"production\",\n                    \"nameAlias\": \"\",\n                    \"ownerKey\": \"\",\n                    \"ownerTag\": \"\"\n                }\n            }\n        }\n    ]\nerror:\n  description: The error information as returned from the APIC\n  returned: failure\n  type: dict\n  sample:\n    {\n        \"code\": \"122\",\n        \"text\": \"unknown managed object class foo\"\n    }\nraw:\n  description: The raw output returned by the APIC REST API (xml or json)\n  returned: parse error\n  type: string\n  sample: '<?xml version=\"1.0\" encoding=\"UTF-8\"?><imdata totalCount=\"1\"><error code=\"122\" text=\"unknown managed object class foo\"/></imdata>'\nsent:\n  description: The actual/minimal configuration pushed to the APIC\n  returned: info\n  type: list\n  sample:\n    {\n        \"fvTenant\": {\n            \"attributes\": {\n                \"descr\": \"Production environment\"\n            }\n        }\n    }\nprevious:\n  description: The original configuration from the APIC before the module has started\n  returned: info\n  type: list\n  sample:\n    [\n        {\n            \"fvTenant\": {\n                \"attributes\": {\n                    \"descr\": \"Production\",\n                    \"dn\": \"uni/tn-production\",\n                    \"name\": \"production\",\n                    \"nameAlias\": \"\",\n                    \"ownerKey\": \"\",\n                    \"ownerTag\": \"\"\n                }\n            }\n        }\n    ]\nproposed:\n  description: The assembled configuration from the user-provided parameters\n  returned: info\n  type: dict\n  sample:\n    {\n        \"fvTenant\": {\n            \"attributes\": {\n                \"descr\": \"Production environment\",\n                \"name\": \"production\"\n            }\n        }\n    }\nfilter_string:\n  description: The filter string used for the request\n  returned: failure or debug\n  type: string\n  sample: ?rsp-prop-include=config-only\nmethod:\n  description: The HTTP method used for the request to the APIC\n  returned: failure or debug\n  type: string\n  sample: POST\nresponse:\n  description: The HTTP response from the APIC\n  returned: failure or debug\n  type: string\n  sample: OK (30 bytes)\nstatus:\n  description: The HTTP status from the APIC\n  returned: failure or debug\n  type: int\n  sample: 200\nurl:\n  description: The HTTP url used for the request to the APIC\n  returned: failure or debug\n  type: string\n  sample: https://10.11.12.13/api/mo/uni/tn-production.json\n'''\n\nfrom ansible.module_utils.network.aci.aci import ACIModule, aci_argument_spec\nfrom ansible.module_utils.basic import AnsibleModule\n\n\ndef main():\n    argument_spec = aci_argument_spec()\n    argument_spec.update(\n        admin_state=dict(type='raw'),  \n        description=dict(type='str', aliases=['descr']),\n        dst_group=dict(type='str'),\n        src_group=dict(type='str', required=False, aliases=['name']),  \n        state=dict(type='str', default='present', choices=['absent', 'present', 'query']),\n        tenant=dict(type='str', required=False, aliases=['tenant_name']),  \n        method=dict(type='str', choices=['delete', 'get', 'post'], aliases=['action'], removed_in_version='2.6'),  \n        protocol=dict(type='str', removed_in_version='2.6'),  \n    )\n\n    module = AnsibleModule(\n        argument_spec=argument_spec,\n        supports_check_mode=True,\n        required_if=[\n            ['state', 'absent', ['src_group', 'tenant']],\n            ['state', 'present', ['src_group', 'tenant']],\n        ],\n    )\n\n    aci = ACIModule(module)\n\n    admin_state = aci.boolean(module.params['admin_state'], 'enabled', 'disabled')\n    description = module.params['description']\n    dst_group = module.params['dst_group']\n    src_group = module.params['src_group']\n    state = module.params['state']\n    tenant = module.params['tenant']\n\n    aci.construct_url(\n        root_class=dict(\n            aci_class='fvTenant',\n            aci_rn='tn-{0}'.format(tenant),\n            filter_target='eq(fvTenant.name, \"{0}\")'.format(tenant),\n            module_object=tenant,\n        ),\n        subclass_1=dict(\n            aci_class='spanSrcGrp',\n            aci_rn='srcgrp-{0}'.format(src_group),\n            filter_target='eq(spanSrcGrp.name, \"{0}\")'.format(src_group),\n            module_object=src_group,\n        ),\n        child_classes=['spanSpanLbl'],\n    )\n\n    aci.get_existing()\n\n    if state == 'present':\n        aci.payload(\n            aci_class='spanSrcGrp',\n            class_config=dict(\n                adminSt=admin_state,\n                descr=description,\n                name=src_group,\n            ),\n            child_configs=[{'spanSpanLbl': {'attributes': {'name': dst_group}}}],\n        )\n\n        aci.get_diff(aci_class='spanSrcGrp')\n\n        aci.post_config()\n\n    elif state == 'absent':\n        aci.delete_config()\n\n    aci.exit_json()\n\n\nif __name__ == \"__main__\":\n    main()\n", "comments": "        module  aci tenant span src group short description  manage span source groups (span srcgrp) description    manage span source groups cisco aci fabrics  notes    the c(tenant) used must exist using module playbook    the m(aci tenant) module used    more information internal apic class b(span srcgrp)   l(the apic management information model reference https   developer cisco com docs apic mim ref )  author    jacob mcgill ( jmcgill298) version added   2 4  options    admin state      description        enable disable span sources      choices    enabled  disabled       default  enabled   description      description        the description span source group      aliases    descr     dst group      description        the span destination group associate source group    src group      description        the name span source group      aliases    name     state      description        use c(present) c(absent) adding removing        use c(query) listing object multiple objects      choices    absent  present  query       default  present   tenant      description        the name tenant      aliases    tenant name   extends documentation fragment  aci      examples   r      aci tenant span src group      host  apic     username  admin     password  somesecretpassword     tenant  production     src group      src group         dst group      dst group         admin state      admin state         description      description          return   r    current    description  the existing configuration apic module finished   returned  success   type  list   sample                               fvtenant                      attributes                          descr    production environment                        dn    uni tn production                        name    production                        namealias                            ownerkey                            ownertag                                                      error    description  the error information returned apic   returned  failure   type  dict   sample                 code    122            text    unknown managed object class foo        raw    description  the raw output returned apic rest api (xml json)   returned  parse error   type  string   sample     xml version  1 0  encoding  utf 8    imdata totalcount  1   error code  122  text  unknown managed object class foo     imdata   sent    description  the actual minimal configuration pushed apic   returned  info   type  list   sample                 fvtenant                  attributes                      descr    production environment                                previous    description  the original configuration apic module started   returned  info   type  list   sample                               fvtenant                      attributes                          descr    production                        dn    uni tn production                        name    production                        namealias                            ownerkey                            ownertag                                                      proposed    description  the assembled configuration user provided parameters   returned  info   type  dict   sample                 fvtenant                  attributes                      descr    production environment                    name    production                                filter string    description  the filter string used request   returned  failure debug   type  string   sample   rsp prop include config method    description  the http method used request apic   returned  failure debug   type  string   sample  post response    description  the http response apic   returned  failure debug   type  string   sample  ok (30 bytes) status    description  the http status apic   returned  failure debug   type  int   sample  200 url    description  the http url used request apic   returned  failure debug   type  string   sample  https   10 11 12 13 api mo uni tn production json         usr bin python        coding  utf 8        gnu general public license v3 0  (see copying https   www gnu org licenses gpl 3 0 txt)    turn boolean v2 9    not required querying objects    not required querying objects    deprecated starting v2 6    deprecated v2 6 ", "content": "#!/usr/bin/python\n# -*- coding: utf-8 -*-\n\n# GNU General Public License v3.0+ (see COPYING or https://www.gnu.org/licenses/gpl-3.0.txt)\n\nfrom __future__ import absolute_import, division, print_function\n__metaclass__ = type\n\nANSIBLE_METADATA = {'metadata_version': '1.1',\n                    'status': ['preview'],\n                    'supported_by': 'community'}\n\nDOCUMENTATION = r'''\n---\nmodule: aci_tenant_span_src_group\nshort_description: Manage SPAN source groups (span:SrcGrp)\ndescription:\n- Manage SPAN source groups on Cisco ACI fabrics.\nnotes:\n- The C(tenant) used must exist before using this module in your playbook.\n  The M(aci_tenant) module can be used for this.\n- More information about the internal APIC class B(span:SrcGrp) from\n  L(the APIC Management Information Model reference,https://developer.cisco.com/docs/apic-mim-ref/).\nauthor:\n- Jacob McGill (@jmcgill298)\nversion_added: '2.4'\noptions:\n  admin_state:\n    description:\n    - Enable or disable the span sources.\n    choices: [ enabled, disabled ]\n    default: enabled\n  description:\n    description:\n    - The description for Span source group.\n    aliases: [ descr ]\n  dst_group:\n    description:\n    - The Span destination group to associate with the source group.\n  src_group:\n    description:\n    - The name of the Span source group.\n    aliases: [ name ]\n  state:\n    description:\n    - Use C(present) or C(absent) for adding or removing.\n    - Use C(query) for listing an object or multiple objects.\n    choices: [ absent, present, query ]\n    default: present\n  tenant:\n    description:\n    - The name of the Tenant.\n    aliases: [ tenant_name ]\nextends_documentation_fragment: aci\n'''\n\nEXAMPLES = r'''\n- aci_tenant_span_src_group:\n    host: apic\n    username: admin\n    password: SomeSecretPassword\n    tenant: production\n    src_group: \"{{ src_group }}\"\n    dst_group: \"{{ dst_group }}\"\n    admin_state: \"{{ admin_state }}\"\n    description: \"{{ description }}\"\n'''\n\nRETURN = r'''\ncurrent:\n  description: The existing configuration from the APIC after the module has finished\n  returned: success\n  type: list\n  sample:\n    [\n        {\n            \"fvTenant\": {\n                \"attributes\": {\n                    \"descr\": \"Production environment\",\n                    \"dn\": \"uni/tn-production\",\n                    \"name\": \"production\",\n                    \"nameAlias\": \"\",\n                    \"ownerKey\": \"\",\n                    \"ownerTag\": \"\"\n                }\n            }\n        }\n    ]\nerror:\n  description: The error information as returned from the APIC\n  returned: failure\n  type: dict\n  sample:\n    {\n        \"code\": \"122\",\n        \"text\": \"unknown managed object class foo\"\n    }\nraw:\n  description: The raw output returned by the APIC REST API (xml or json)\n  returned: parse error\n  type: string\n  sample: '<?xml version=\"1.0\" encoding=\"UTF-8\"?><imdata totalCount=\"1\"><error code=\"122\" text=\"unknown managed object class foo\"/></imdata>'\nsent:\n  description: The actual/minimal configuration pushed to the APIC\n  returned: info\n  type: list\n  sample:\n    {\n        \"fvTenant\": {\n            \"attributes\": {\n                \"descr\": \"Production environment\"\n            }\n        }\n    }\nprevious:\n  description: The original configuration from the APIC before the module has started\n  returned: info\n  type: list\n  sample:\n    [\n        {\n            \"fvTenant\": {\n                \"attributes\": {\n                    \"descr\": \"Production\",\n                    \"dn\": \"uni/tn-production\",\n                    \"name\": \"production\",\n                    \"nameAlias\": \"\",\n                    \"ownerKey\": \"\",\n                    \"ownerTag\": \"\"\n                }\n            }\n        }\n    ]\nproposed:\n  description: The assembled configuration from the user-provided parameters\n  returned: info\n  type: dict\n  sample:\n    {\n        \"fvTenant\": {\n            \"attributes\": {\n                \"descr\": \"Production environment\",\n                \"name\": \"production\"\n            }\n        }\n    }\nfilter_string:\n  description: The filter string used for the request\n  returned: failure or debug\n  type: string\n  sample: ?rsp-prop-include=config-only\nmethod:\n  description: The HTTP method used for the request to the APIC\n  returned: failure or debug\n  type: string\n  sample: POST\nresponse:\n  description: The HTTP response from the APIC\n  returned: failure or debug\n  type: string\n  sample: OK (30 bytes)\nstatus:\n  description: The HTTP status from the APIC\n  returned: failure or debug\n  type: int\n  sample: 200\nurl:\n  description: The HTTP url used for the request to the APIC\n  returned: failure or debug\n  type: string\n  sample: https://10.11.12.13/api/mo/uni/tn-production.json\n'''\n\nfrom ansible.module_utils.network.aci.aci import ACIModule, aci_argument_spec\nfrom ansible.module_utils.basic import AnsibleModule\n\n\ndef main():\n    argument_spec = aci_argument_spec()\n    argument_spec.update(\n        admin_state=dict(type='raw'),  # Turn into a boolean in v2.9\n        description=dict(type='str', aliases=['descr']),\n        dst_group=dict(type='str'),\n        src_group=dict(type='str', required=False, aliases=['name']),  # Not required for querying all objects\n        state=dict(type='str', default='present', choices=['absent', 'present', 'query']),\n        tenant=dict(type='str', required=False, aliases=['tenant_name']),  # Not required for querying all objects\n        method=dict(type='str', choices=['delete', 'get', 'post'], aliases=['action'], removed_in_version='2.6'),  # Deprecated starting from v2.6\n        protocol=dict(type='str', removed_in_version='2.6'),  # Deprecated in v2.6\n    )\n\n    module = AnsibleModule(\n        argument_spec=argument_spec,\n        supports_check_mode=True,\n        required_if=[\n            ['state', 'absent', ['src_group', 'tenant']],\n            ['state', 'present', ['src_group', 'tenant']],\n        ],\n    )\n\n    aci = ACIModule(module)\n\n    admin_state = aci.boolean(module.params['admin_state'], 'enabled', 'disabled')\n    description = module.params['description']\n    dst_group = module.params['dst_group']\n    src_group = module.params['src_group']\n    state = module.params['state']\n    tenant = module.params['tenant']\n\n    aci.construct_url(\n        root_class=dict(\n            aci_class='fvTenant',\n            aci_rn='tn-{0}'.format(tenant),\n            filter_target='eq(fvTenant.name, \"{0}\")'.format(tenant),\n            module_object=tenant,\n        ),\n        subclass_1=dict(\n            aci_class='spanSrcGrp',\n            aci_rn='srcgrp-{0}'.format(src_group),\n            filter_target='eq(spanSrcGrp.name, \"{0}\")'.format(src_group),\n            module_object=src_group,\n        ),\n        child_classes=['spanSpanLbl'],\n    )\n\n    aci.get_existing()\n\n    if state == 'present':\n        aci.payload(\n            aci_class='spanSrcGrp',\n            class_config=dict(\n                adminSt=admin_state,\n                descr=description,\n                name=src_group,\n            ),\n            child_configs=[{'spanSpanLbl': {'attributes': {'name': dst_group}}}],\n        )\n\n        aci.get_diff(aci_class='spanSrcGrp')\n\n        aci.post_config()\n\n    elif state == 'absent':\n        aci.delete_config()\n\n    aci.exit_json()\n\n\nif __name__ == \"__main__\":\n    main()\n", "description": "Ansible is a radically simple IT automation platform that makes your applications and systems easier to deploy. Avoid writing scripts or custom code to deploy and update your applications\u2014 automate in a language that approaches plain English, using SSH, with no agents to install on remote systems.", "file_name": "aci_tenant_span_src_group.py", "id": "ab8e0421aada17f12eac10665ff4f76c", "language": "Python", "project_name": "ansible", "quality": "", "save_path": "/home/ubuntu/test_files/clean/python/ansible-ansible/ansible-ansible-d30554b/lib/ansible/modules/network/aci/aci_tenant_span_src_group.py", "save_time": "", "source": "", "update_at": "2018-03-18T14:08:28Z", "url": "https://github.com/ansible/ansible", "wiki": false}