{"author": "sympy", "code": "", "comments": "", "content": "", "description": "A computer algebra system written in pure Python", "file_name": "__init__.py", "id": "b4be9f888730e931987001af8c39f42f", "language": "Python", "project_name": "sympy", "quality": "", "save_path": "/home/ubuntu/test_files/clean/python/sympy-sympy/sympy-sympy-205da79/sympy/sets/handlers/__init__.py", "save_time": "", "source": "", "update_at": "2018-03-18T16:35:56Z", "url": "https://github.com/sympy/sympy", "wiki": true}