{"author": "django", "code": "from django.conf.urls import url\n\nfrom .views import ArticleFormView\n\nurlpatterns = [\n    url(r'^model_form/(?P<pk>[0-9]+)/$', ArticleFormView.as_view(), name=\"article_form\"),\n]\n", "comments": "", "content": "from django.conf.urls import url\n\nfrom .views import ArticleFormView\n\nurlpatterns = [\n    url(r'^model_form/(?P<pk>[0-9]+)/$', ArticleFormView.as_view(), name=\"article_form\"),\n]\n", "description": "The Web framework for perfectionists with deadlines.", "file_name": "urls.py", "id": "e5fffd70129183e86ea06f51f1485d28", "language": "Python", "project_name": "django", "quality": "", "save_path": "/home/ubuntu/test_files/clean/python/django-django/django-django-274e3e2/tests/forms_tests/urls.py", "save_time": "", "source": "", "update_at": "2018-03-18T13:39:10Z", "url": "https://github.com/django/django", "wiki": false}