{"author": "donnemartin", "code": "from nose.tools import assert_equal, assert_raises\n\n\nclass TestArray(object):\n\n    def test_merge_into(self):\n        array = Array()\n        assert_raises(TypeError, array.merge_into, None, None, None, None)\n        assert_raises(ValueError, array.merge_into, [1], [2], -1, -1)\n        a = [1, 2, 3]\n        assert_equal(array.merge_into(a, [], len(a), 0), [1, 2, 3])\n        a = [1, 2, 3]\n        assert_equal(array.merge_into(a, [], len(a), 0), [1, 2, 3])\n        a = [1,  3,  5,  7,  9,  None,  None,  None]\n        b = [4,  5,  6]\n        expected = [1, 3, 4, 5, 5, 6, 7, 9]\n        assert_equal(array.merge_into(a, b, 5, len(b)), expected)\n        print('Success: test_merge_into')\n\n\ndef main():\n    test = TestArray()\n    test.test_merge_into()\n\n\nif __name__ == '__main__':\n    main()", "comments": "", "content": "from nose.tools import assert_equal, assert_raises\n\n\nclass TestArray(object):\n\n    def test_merge_into(self):\n        array = Array()\n        assert_raises(TypeError, array.merge_into, None, None, None, None)\n        assert_raises(ValueError, array.merge_into, [1], [2], -1, -1)\n        a = [1, 2, 3]\n        assert_equal(array.merge_into(a, [], len(a), 0), [1, 2, 3])\n        a = [1, 2, 3]\n        assert_equal(array.merge_into(a, [], len(a), 0), [1, 2, 3])\n        a = [1,  3,  5,  7,  9,  None,  None,  None]\n        b = [4,  5,  6]\n        expected = [1, 3, 4, 5, 5, 6, 7, 9]\n        assert_equal(array.merge_into(a, b, 5, len(b)), expected)\n        print('Success: test_merge_into')\n\n\ndef main():\n    test = TestArray()\n    test.test_merge_into()\n\n\nif __name__ == '__main__':\n    main()", "description": "Interactive Python coding interview challenges (algorithms and data structures).  Includes Anki flashcards.", "file_name": "test_merge_into.py", "id": "e8bb800c8ffc5580944e683dedf7c2da", "language": "Python", "project_name": "interactive-coding-challenges", "quality": "", "save_path": "/home/ubuntu/test_files/clean/network_test/donnemartin-interactive-coding-challenges/donnemartin-interactive-coding-challenges-6eb3114/sorting_searching/merge_into/test_merge_into.py", "save_time": "", "source": "", "update_at": "2018-03-13T21:01:52Z", "url": "https://github.com/donnemartin/interactive-coding-challenges", "wiki": true}