{
  "7508411": {
    "updated_at": "2018-03-26T16:06:25Z",
    "stars": 31777
  },
  "22790488": {
    "updated_at": "2018-03-26T16:08:11Z",
    "stars": 31112
  },
  "507775": {
    "updated_at": "2018-03-26T15:11:27Z",
    "stars": 29732
  },
  "892275": {
    "updated_at": "2018-03-26T15:24:19Z",
    "stars": 27006
  },
  "5152285": {
    "updated_at": "2018-03-26T16:00:04Z",
    "stars": 25710
  },
  "20300177": {
    "updated_at": "2018-03-26T16:20:09Z",
    "stars": 23000
  },
  "6296790": {
    "updated_at": "2018-03-26T16:08:45Z",
    "stars": 22619
  },
  "19148949": {
    "updated_at": "2018-03-26T16:04:59Z",
    "stars": 21225
  },
  "81975372": {
    "updated_at": "2018-03-26T16:28:17Z",
    "stars": 20944
  }
}